README.md
setup.py
simple_machine_learning.egg-info/PKG-INFO
simple_machine_learning.egg-info/SOURCES.txt
simple_machine_learning.egg-info/dependency_links.txt
simple_machine_learning.egg-info/requires.txt
simple_machine_learning.egg-info/top_level.txt
simple_machine_learning.egg-info/zip-safe
simple_ml/ensemble/__init__.py
simple_ml/ensemble/model.py
simple_ml/linear/__init__.py
simple_ml/linear/model.py
simple_ml/linear/test.py
simple_ml/nn/__init__.py
simple_ml/nn/activation.py
simple_ml/nn/initializer.py
simple_ml/nn/layer.py
simple_ml/nn/loss.py
simple_ml/nn/model.py
simple_ml/nn/ops.py
simple_ml/nn/optimizer.py
simple_ml/nn/regularizer.py
simple_ml/nn/utils.py
simple_ml/preprocessing/__init__.py
simple_ml/preprocessing/feature.py
simple_ml/preprocessing/general.py
simple_ml/preprocessing/test.py
simple_ml/utils/__init__.py
simple_ml/utils/distance.py
simple_ml/utils/funcs.py
simple_ml/utils/metric.py
simple_ml/utils/test.py
simple_ml/ensemble/__init__.py
simple_ml/ensemble/model.py
simple_ml/linear/__init__.py
simple_ml/linear/model.py
simple_ml/linear/test.py
simple_ml/nn/__init__.py
simple_ml/nn/activation.py
simple_ml/nn/initializer.py
simple_ml/nn/layer.py
simple_ml/nn/loss.py
simple_ml/nn/model.py
simple_ml/nn/ops.py
simple_ml/nn/optimizer.py
simple_ml/nn/regularizer.py
simple_ml/nn/utils.py
simple_ml/preprocessing/__init__.py
simple_ml/preprocessing/feature.py
simple_ml/preprocessing/general.py
simple_ml/preprocessing/test.py
simple_ml/utils/__init__.py
simple_ml/utils/distance.py
simple_ml/utils/funcs.py
simple_ml/utils/metric.py
simple_ml/utils/test.py