Metadata-Version: 1.1
Name: simple-machine-learning
Version: 0.1.4
Summary: simple: simple machine learning framework.
Home-page: https://github.com/lizhaoliu-Lec/simple_ml
Author: lizhaoliu
Author-email: 2524463910@qq.com
License: MIT
Platform: UNKNOWN
Classifier: License :: OSI Approved :: MIT License
Classifier: Programming Language :: Python
Classifier: Intended Audience :: Developers
Classifier: Operating System :: OS Independent
